{
    "name": "Global Information",
    "numberOfRequests": {
        "total": 3,
        "ok": 3,
        "ko": 0
    },
    "minResponseTime": {
        "total": 1136,
        "ok": 1136,
        "ko": 0
    },
    "maxResponseTime": {
        "total": 11278,
        "ok": 11278,
        "ko": 0
    },
    "meanResponseTime": {
        "total": 4689,
        "ok": 4689,
        "ko": 0
    },
    "standardDeviation": {
        "total": 4664,
        "ok": 4664,
        "ko": 0
    },
    "percentiles1": {
        "total": 1652,
        "ok": 1652,
        "ko": 0
    },
    "percentiles2": {
        "total": 6465,
        "ok": 6465,
        "ko": 0
    },
    "percentiles3": {
        "total": 10315,
        "ok": 10315,
        "ko": 0
    },
    "percentiles4": {
        "total": 11085,
        "ok": 11085,
        "ko": 0
    },
    "group1": {
    "name": "t < 800 ms",
    "count": 0,
    "percentage": 0
},
    "group2": {
    "name": "800 ms < t < 1200 ms",
    "count": 1,
    "percentage": 33
},
    "group3": {
    "name": "t > 1200 ms",
    "count": 2,
    "percentage": 67
},
    "group4": {
    "name": "failed",
    "count": 0,
    "percentage": 0
},
    "meanNumberOfRequestsPerSecond": {
        "total": 0.2,
        "ok": 0.2,
        "ko": 0
    }
}